madmax/__init__.py
madmax/client.py
madmax/enums.py
madmax/errors.py
madmax/gateway.py
madmax/types/__init__.py
madmax/types/message.py
madmax-0.0.3.dist-info/METADATA
madmax-0.0.3.dist-info/WHEEL
madmax-0.0.3.dist-info/licenses/LICENSE.txt
madmax-0.0.3.dist-info/RECORD
