Metadata-Version: 2.4
Name: madmax
Version: 0.0.3
Summary: Unofficial Async Client for MAX Messenger (OneMe)
Project-URL: Homepage, https://github.com/ctrljapan/MadMax
Project-URL: Bug Tracker, https://github.com/ctrljapan/MadMax/issues
Author-email: CTRLJapan <ctrljapantop@gmail.com>
License-File: LICENSE.txt
Requires-Python: >=3.7
Requires-Dist: aiohttp
